[
 {
  "bulk_actions": 0,
  "dashboard": 0,
  "desk_access": 0,
  "disabled": 0,
  "docstatus": 0,
  "doctype": "Role",
  "form_sidebar": 0,
  "home_page": null,
  "is_custom": 0,
  "list_sidebar": 0,
  "modified": "2022-05-27 10:50:05.457927",
  "name": "Guest",
  "notifications": 0,
  "restrict_to_domain": null,
  "role_name": "Guest",
  "search_bar": 0,
  "timeline": 0,
  "two_factor_auth": 0,
  "view_switcher": 0
 },
 {
  "bulk_actions": 0,
  "dashboard": 0,
  "desk_access": 1,
  "disabled": 0,
  "docstatus": 0,
  "doctype": "Role",
  "form_sidebar": 1,
  "home_page": null,
  "is_custom": 0,
  "list_sidebar": 1,
  "modified": "2022-07-28 21:17:16.187372",
  "name": "All",
  "notifications": 0,
  "restrict_to_domain": null,
  "role_name": "All",
  "search_bar": 0,
  "timeline": 0,
  "two_factor_auth": 0,
  "view_switcher": 0
 },
 {
  "bulk_actions": 0,
  "dashboard": 0,
  "desk_access": 1,
  "disabled": 0,
  "docstatus": 0,
  "doctype": "Role",
  "form_sidebar": 0,
  "home_page": null,
  "is_custom": 0,
  "list_sidebar": 0,
  "modified": "2022-05-27 10:50:05.466412",
  "name": "System Manager",
  "notifications": 0,
  "restrict_to_domain": null,
  "role_name": "System Manager",
  "search_bar": 0,
  "timeline": 0,
  "two_factor_auth": 0,
  "view_switcher": 0
 },
 {
  "bulk_actions": 0,
  "dashboard": 0,
  "desk_access": 1,
  "disabled": 0,
  "docstatus": 0,
  "doctype": "Role",
  "form_sidebar": 0,
  "home_page": null,
  "is_custom": 0,
  "list_sidebar": 0,
  "modified": "2022-05-27 10:50:05.470349",
  "name": "Administrator",
  "notifications": 0,
  "restrict_to_domain": null,
  "role_name": "Administrator",
  "search_bar": 0,
  "timeline": 0,
  "two_factor_auth": 0,
  "view_switcher": 0
 },
 {
  "bulk_actions": 0,
  "dashboard": 0,
  "desk_access": 1,
  "disabled": 0,
  "docstatus": 0,
  "doctype": "Role",
  "form_sidebar": 0,
  "home_page": null,
  "is_custom": 0,
  "list_sidebar": 0,
  "modified": "2022-05-27 10:50:05.927276",
  "name": "Website Manager",
  "notifications": 0,
  "restrict_to_domain": null,
  "role_name": "Website Manager",
  "search_bar": 0,
  "timeline": 0,
  "two_factor_auth": 0,
  "view_switcher": 0
 },
 {
  "bulk_actions": 0,
  "dashboard": 0,
  "desk_access": 1,
  "disabled": 0,
  "docstatus": 0,
  "doctype": "Role",
  "form_sidebar": 0,
  "home_page": null,
  "is_custom": 0,
  "list_sidebar": 0,
  "modified": "2022-05-27 10:50:06.530374",
  "name": "Dashboard Manager",
  "notifications": 0,
  "restrict_to_domain": null,
  "role_name": "Dashboard Manager",
  "search_bar": 0,
  "timeline": 0,
  "two_factor_auth": 0,
  "view_switcher": 0
 },
 {
  "bulk_actions": 0,
  "dashboard": 0,
  "desk_access": 1,
  "disabled": 0,
  "docstatus": 0,
  "doctype": "Role",
  "form_sidebar": 0,
  "home_page": null,
  "is_custom": 0,
  "list_sidebar": 0,
  "modified": "2022-05-27 10:50:07.332834",
  "name": "Workspace Manager",
  "notifications": 0,
  "restrict_to_domain": null,
  "role_name": "Workspace Manager",
  "search_bar": 0,
  "timeline": 0,
  "two_factor_auth": 0,
  "view_switcher": 0
 },
 {
  "bulk_actions": 0,
  "dashboard": 0,
  "desk_access": 1,
  "disabled": 0,
  "docstatus": 0,
  "doctype": "Role",
  "form_sidebar": 0,
  "home_page": null,
  "is_custom": 0,
  "list_sidebar": 0,
  "modified": "2022-05-27 10:50:08.863668",
  "name": "Inbox User",
  "notifications": 0,
  "restrict_to_domain": null,
  "role_name": "Inbox User",
  "search_bar": 0,
  "timeline": 0,
  "two_factor_auth": 0,
  "view_switcher": 0
 },
 {
  "bulk_actions": 0,
  "dashboard": 0,
  "desk_access": 1,
  "disabled": 0,
  "docstatus": 0,
  "doctype": "Role",
  "form_sidebar": 0,
  "home_page": null,
  "is_custom": 0,
  "list_sidebar": 0,
  "modified": "2022-05-27 10:50:10.463992",
  "name": "Prepared Report User",
  "notifications": 0,
  "restrict_to_domain": null,
  "role_name": "Prepared Report User",
  "search_bar": 0,
  "timeline": 0,
  "two_factor_auth": 0,
  "view_switcher": 0
 },
 {
  "bulk_actions": 0,
  "dashboard": 0,
  "desk_access": 1,
  "disabled": 0,
  "docstatus": 0,
  "doctype": "Role",
  "form_sidebar": 0,
  "home_page": null,
  "is_custom": 0,
  "list_sidebar": 0,
  "modified": "2022-05-27 10:50:10.576865",
  "name": "Report Manager",
  "notifications": 0,
  "restrict_to_domain": null,
  "role_name": "Report Manager",
  "search_bar": 0,
  "timeline": 0,
  "two_factor_auth": 0,
  "view_switcher": 0
 },
 {
  "bulk_actions": 0,
  "dashboard": 0,
  "desk_access": 1,
  "disabled": 0,
  "docstatus": 0,
  "doctype": "Role",
  "form_sidebar": 0,
  "home_page": null,
  "is_custom": 0,
  "list_sidebar": 0,
  "modified": "2022-05-27 10:50:11.433611",
  "name": "Script Manager",
  "notifications": 0,
  "restrict_to_domain": null,
  "role_name": "Script Manager",
  "search_bar": 0,
  "timeline": 0,
  "two_factor_auth": 0,
  "view_switcher": 0
 },
 {
  "bulk_actions": 0,
  "dashboard": 0,
  "desk_access": 1,
  "disabled": 0,
  "docstatus": 0,
  "doctype": "Role",
  "form_sidebar": 0,
  "home_page": null,
  "is_custom": 0,
  "list_sidebar": 0,
  "modified": "2022-05-27 10:50:13.925277",
  "name": "Blogger",
  "notifications": 0,
  "restrict_to_domain": null,
  "role_name": "Blogger",
  "search_bar": 0,
  "timeline": 0,
  "two_factor_auth": 0,
  "view_switcher": 0
 },
 {
  "bulk_actions": 0,
  "dashboard": 0,
  "desk_access": 1,
  "disabled": 0,
  "docstatus": 0,
  "doctype": "Role",
  "form_sidebar": 0,
  "home_page": null,
  "is_custom": 0,
  "list_sidebar": 0,
  "modified": "2022-05-27 10:50:15.630885",
  "name": "Knowledge Base Contributor",
  "notifications": 0,
  "restrict_to_domain": null,
  "role_name": "Knowledge Base Contributor",
  "search_bar": 0,
  "timeline": 0,
  "two_factor_auth": 0,
  "view_switcher": 0
 },
 {
  "bulk_actions": 0,
  "dashboard": 0,
  "desk_access": 1,
  "disabled": 0,
  "docstatus": 0,
  "doctype": "Role",
  "form_sidebar": 0,
  "home_page": null,
  "is_custom": 0,
  "list_sidebar": 0,
  "modified": "2022-05-27 10:50:15.636167",
  "name": "Knowledge Base Editor",
  "notifications": 0,
  "restrict_to_domain": null,
  "role_name": "Knowledge Base Editor",
  "search_bar": 0,
  "timeline": 0,
  "two_factor_auth": 0,
  "view_switcher": 0
 },
 {
  "bulk_actions": 0,
  "dashboard": 0,
  "desk_access": 1,
  "disabled": 0,
  "docstatus": 0,
  "doctype": "Role",
  "form_sidebar": 0,
  "home_page": null,
  "is_custom": 0,
  "list_sidebar": 0,
  "modified": "2022-05-27 10:50:18.035354",
  "name": "Newsletter Manager",
  "notifications": 0,
  "restrict_to_domain": null,
  "role_name": "Newsletter Manager",
  "search_bar": 0,
  "timeline": 0,
  "two_factor_auth": 0,
  "view_switcher": 0
 },
 {
  "bulk_actions": 0,
  "dashboard": 0,
  "desk_access": 1,
  "disabled": 0,
  "docstatus": 0,
  "doctype": "Role",
  "form_sidebar": 0,
  "home_page": null,
  "is_custom": 0,
  "list_sidebar": 0,
  "modified": "2022-05-27 10:50:19.468393",
  "name": "Purchase User",
  "notifications": 0,
  "restrict_to_domain": null,
  "role_name": "Purchase User",
  "search_bar": 0,
  "timeline": 0,
  "two_factor_auth": 0,
  "view_switcher": 0
 },
 {
  "bulk_actions": 0,
  "dashboard": 0,
  "desk_access": 1,
  "disabled": 0,
  "docstatus": 0,
  "doctype": "Role",
  "form_sidebar": 0,
  "home_page": null,
  "is_custom": 0,
  "list_sidebar": 0,
  "modified": "2022-05-27 10:50:19.474104",
  "name": "Accounts User",
  "notifications": 0,
  "restrict_to_domain": null,
  "role_name": "Accounts User",
  "search_bar": 0,
  "timeline": 0,
  "two_factor_auth": 0,
  "view_switcher": 0
 },
 {
  "bulk_actions": 0,
  "dashboard": 0,
  "desk_access": 1,
  "disabled": 0,
  "docstatus": 0,
  "doctype": "Role",
  "form_sidebar": 0,
  "home_page": null,
  "is_custom": 0,
  "list_sidebar": 0,
  "modified": "2022-10-20 23:16:40.405234",
  "name": "Sales User",
  "notifications": 0,
  "restrict_to_domain": null,
  "role_name": "Sales User",
  "search_bar": 1,
  "timeline": 0,
  "two_factor_auth": 0,
  "view_switcher": 0
 },
 {
  "bulk_actions": 0,
  "dashboard": 0,
  "desk_access": 1,
  "disabled": 0,
  "docstatus": 0,
  "doctype": "Role",
  "form_sidebar": 0,
  "home_page": null,
  "is_custom": 0,
  "list_sidebar": 0,
  "modified": "2022-05-27 10:50:25.837199",
  "name": "Maintenance User",
  "notifications": 0,
  "restrict_to_domain": null,
  "role_name": "Maintenance User",
  "search_bar": 0,
  "timeline": 0,
  "two_factor_auth": 0,
  "view_switcher": 0
 },
 {
  "bulk_actions": 0,
  "dashboard": 0,
  "desk_access": 1,
  "disabled": 0,
  "docstatus": 0,
  "doctype": "Role",
  "form_sidebar": 0,
  "home_page": null,
  "is_custom": 0,
  "list_sidebar": 0,
  "modified": "2022-05-27 10:50:26.068813",
  "name": "Sales Master Manager",
  "notifications": 0,
  "restrict_to_domain": null,
  "role_name": "Sales Master Manager",
  "search_bar": 0,
  "timeline": 0,
  "two_factor_auth": 0,
  "view_switcher": 0
 },
 {
  "bulk_actions": 0,
  "dashboard": 0,
  "desk_access": 1,
  "disabled": 0,
  "docstatus": 0,
  "doctype": "Role",
  "form_sidebar": 0,
  "home_page": null,
  "is_custom": 0,
  "list_sidebar": 0,
  "modified": "2022-05-27 10:50:26.075450",
  "name": "Purchase Master Manager",
  "notifications": 0,
  "restrict_to_domain": null,
  "role_name": "Purchase Master Manager",
  "search_bar": 0,
  "timeline": 0,
  "two_factor_auth": 0,
  "view_switcher": 0
 },
 {
  "bulk_actions": 0,
  "dashboard": 0,
  "desk_access": 1,
  "disabled": 0,
  "docstatus": 0,
  "doctype": "Role",
  "form_sidebar": 0,
  "home_page": null,
  "is_custom": 0,
  "list_sidebar": 0,
  "modified": "2022-05-27 10:50:26.081310",
  "name": "Purchase Manager",
  "notifications": 0,
  "restrict_to_domain": null,
  "role_name": "Purchase Manager",
  "search_bar": 0,
  "timeline": 0,
  "two_factor_auth": 0,
  "view_switcher": 0
 },
 {
  "bulk_actions": 0,
  "dashboard": 0,
  "desk_access": 1,
  "disabled": 0,
  "docstatus": 0,
  "doctype": "Role",
  "form_sidebar": 0,
  "home_page": null,
  "is_custom": 0,
  "list_sidebar": 0,
  "modified": "2022-05-27 10:50:26.090253",
  "name": "Accounts Manager",
  "notifications": 0,
  "restrict_to_domain": null,
  "role_name": "Accounts Manager",
  "search_bar": 0,
  "timeline": 0,
  "two_factor_auth": 0,
  "view_switcher": 0
 },
 {
  "bulk_actions": 0,
  "dashboard": 0,
  "desk_access": 1,
  "disabled": 0,
  "docstatus": 0,
  "doctype": "Role",
  "form_sidebar": 0,
  "home_page": null,
  "is_custom": 0,
  "list_sidebar": 0,
  "modified": "2022-05-27 10:50:26.096083",
  "name": "Maintenance Manager",
  "notifications": 0,
  "restrict_to_domain": null,
  "role_name": "Maintenance Manager",
  "search_bar": 0,
  "timeline": 0,
  "two_factor_auth": 0,
  "view_switcher": 0
 },
 {
  "bulk_actions": 0,
  "dashboard": 0,
  "desk_access": 1,
  "disabled": 0,
  "docstatus": 0,
  "doctype": "Role",
  "form_sidebar": 0,
  "home_page": null,
  "is_custom": 0,
  "list_sidebar": 0,
  "modified": "2022-05-27 10:50:26.105371",
  "name": "Sales Manager",
  "notifications": 0,
  "restrict_to_domain": null,
  "role_name": "Sales Manager",
  "search_bar": 0,
  "timeline": 0,
  "two_factor_auth": 0,
  "view_switcher": 0
 },
 {
  "bulk_actions": 1,
  "dashboard": 1,
  "desk_access": 1,
  "disabled": 0,
  "docstatus": 0,
  "doctype": "Role",
  "form_sidebar": 1,
  "home_page": null,
  "is_custom": 0,
  "list_sidebar": 1,
  "modified": "2022-05-27 10:50:32.523462",
  "name": "Translator",
  "notifications": 1,
  "restrict_to_domain": null,
  "role_name": "Translator",
  "search_bar": 1,
  "timeline": 1,
  "two_factor_auth": 0,
  "view_switcher": 1
 },
 {
  "bulk_actions": 0,
  "dashboard": 0,
  "desk_access": 1,
  "disabled": 0,
  "docstatus": 0,
  "doctype": "Role",
  "form_sidebar": 0,
  "home_page": null,
  "is_custom": 0,
  "list_sidebar": 0,
  "modified": "2022-05-27 11:01:44.382968",
  "name": "Auditor",
  "notifications": 0,
  "restrict_to_domain": null,
  "role_name": "Auditor",
  "search_bar": 0,
  "timeline": 0,
  "two_factor_auth": 0,
  "view_switcher": 0
 },
 {
  "bulk_actions": 0,
  "dashboard": 0,
  "desk_access": 1,
  "disabled": 0,
  "docstatus": 0,
  "doctype": "Role",
  "form_sidebar": 0,
  "home_page": null,
  "is_custom": 0,
  "list_sidebar": 0,
  "modified": "2022-05-27 11:01:51.357230",
  "name": "Employee",
  "notifications": 0,
  "restrict_to_domain": null,
  "role_name": "Employee",
  "search_bar": 0,
  "timeline": 0,
  "two_factor_auth": 0,
  "view_switcher": 0
 },
 {
  "bulk_actions": 0,
  "dashboard": 0,
  "desk_access": 1,
  "disabled": 0,
  "docstatus": 0,
  "doctype": "Role",
  "form_sidebar": 0,
  "home_page": null,
  "is_custom": 0,
  "list_sidebar": 0,
  "modified": "2022-05-27 11:01:51.389227",
  "name": "Stock User",
  "notifications": 0,
  "restrict_to_domain": null,
  "role_name": "Stock User",
  "search_bar": 0,
  "timeline": 0,
  "two_factor_auth": 0,
  "view_switcher": 0
 },
 {
  "bulk_actions": 0,
  "dashboard": 0,
  "desk_access": 1,
  "disabled": 0,
  "docstatus": 0,
  "doctype": "Role",
  "form_sidebar": 0,
  "home_page": null,
  "is_custom": 0,
  "list_sidebar": 0,
  "modified": "2022-05-27 11:02:04.039144",
  "name": "HR Manager",
  "notifications": 0,
  "restrict_to_domain": null,
  "role_name": "HR Manager",
  "search_bar": 0,
  "timeline": 0,
  "two_factor_auth": 0,
  "view_switcher": 0
 },
 {
  "bulk_actions": 0,
  "dashboard": 0,
  "desk_access": 1,
  "disabled": 0,
  "docstatus": 0,
  "doctype": "Role",
  "form_sidebar": 0,
  "home_page": null,
  "is_custom": 0,
  "list_sidebar": 0,
  "modified": "2022-05-27 11:02:06.472706",
  "name": "Manufacturing Manager",
  "notifications": 0,
  "restrict_to_domain": null,
  "role_name": "Manufacturing Manager",
  "search_bar": 0,
  "timeline": 0,
  "two_factor_auth": 0,
  "view_switcher": 0
 },
 {
  "bulk_actions": 0,
  "dashboard": 0,
  "desk_access": 1,
  "disabled": 0,
  "docstatus": 0,
  "doctype": "Role",
  "form_sidebar": 0,
  "home_page": null,
  "is_custom": 0,
  "list_sidebar": 0,
  "modified": "2022-05-27 11:02:08.142122",
  "name": "Stock Manager",
  "notifications": 0,
  "restrict_to_domain": null,
  "role_name": "Stock Manager",
  "search_bar": 0,
  "timeline": 0,
  "two_factor_auth": 0,
  "view_switcher": 0
 },
 {
  "bulk_actions": 0,
  "dashboard": 0,
  "desk_access": 1,
  "disabled": 0,
  "docstatus": 0,
  "doctype": "Role",
  "form_sidebar": 0,
  "home_page": null,
  "is_custom": 0,
  "list_sidebar": 0,
  "modified": "2022-05-27 11:02:09.516236",
  "name": "Projects User",
  "notifications": 0,
  "restrict_to_domain": null,
  "role_name": "Projects User",
  "search_bar": 0,
  "timeline": 0,
  "two_factor_auth": 0,
  "view_switcher": 0
 },
 {
  "bulk_actions": 0,
  "dashboard": 0,
  "desk_access": 1,
  "disabled": 0,
  "docstatus": 0,
  "doctype": "Role",
  "form_sidebar": 0,
  "home_page": null,
  "is_custom": 0,
  "list_sidebar": 0,
  "modified": "2022-05-27 11:02:10.019788",
  "name": "Projects Manager",
  "notifications": 0,
  "restrict_to_domain": null,
  "role_name": "Projects Manager",
  "search_bar": 0,
  "timeline": 0,
  "two_factor_auth": 0,
  "view_switcher": 0
 },
 {
  "bulk_actions": 0,
  "dashboard": 0,
  "desk_access": 1,
  "disabled": 0,
  "docstatus": 0,
  "doctype": "Role",
  "form_sidebar": 0,
  "home_page": null,
  "is_custom": 0,
  "list_sidebar": 0,
  "modified": "2022-05-27 11:02:11.012991",
  "name": "Manufacturing User",
  "notifications": 0,
  "restrict_to_domain": null,
  "role_name": "Manufacturing User",
  "search_bar": 0,
  "timeline": 0,
  "two_factor_auth": 0,
  "view_switcher": 0
 },
 {
  "bulk_actions": 0,
  "dashboard": 0,
  "desk_access": 1,
  "disabled": 0,
  "docstatus": 0,
  "doctype": "Role",
  "form_sidebar": 0,
  "home_page": null,
  "is_custom": 0,
  "list_sidebar": 0,
  "modified": "2022-05-27 11:02:11.043158",
  "name": "HR User",
  "notifications": 0,
  "restrict_to_domain": null,
  "role_name": "HR User",
  "search_bar": 0,
  "timeline": 0,
  "two_factor_auth": 0,
  "view_switcher": 0
 },
 {
  "bulk_actions": 0,
  "dashboard": 0,
  "desk_access": 1,
  "disabled": 0,
  "docstatus": 0,
  "doctype": "Role",
  "form_sidebar": 0,
  "home_page": null,
  "is_custom": 0,
  "list_sidebar": 0,
  "modified": "2022-05-27 11:02:14.840026",
  "name": "Item Manager",
  "notifications": 0,
  "restrict_to_domain": null,
  "role_name": "Item Manager",
  "search_bar": 0,
  "timeline": 0,
  "two_factor_auth": 0,
  "view_switcher": 0
 },
 {
  "bulk_actions": 0,
  "dashboard": 0,
  "desk_access": 0,
  "disabled": 0,
  "docstatus": 0,
  "doctype": "Role",
  "form_sidebar": 0,
  "home_page": null,
  "is_custom": 0,
  "list_sidebar": 0,
  "modified": "2022-07-28 21:12:20.711699",
  "name": "Customer",
  "notifications": 0,
  "restrict_to_domain": null,
  "role_name": "Customer",
  "search_bar": 0,
  "timeline": 0,
  "two_factor_auth": 0,
  "view_switcher": 0
 },
 {
  "bulk_actions": 0,
  "dashboard": 0,
  "desk_access": 1,
  "disabled": 0,
  "docstatus": 0,
  "doctype": "Role",
  "form_sidebar": 0,
  "home_page": null,
  "is_custom": 0,
  "list_sidebar": 0,
  "modified": "2022-05-27 11:02:18.117214",
  "name": "Academics User",
  "notifications": 0,
  "restrict_to_domain": null,
  "role_name": "Academics User",
  "search_bar": 0,
  "timeline": 0,
  "two_factor_auth": 0,
  "view_switcher": 0
 },
 {
  "bulk_actions": 0,
  "dashboard": 0,
  "desk_access": 1,
  "disabled": 0,
  "docstatus": 0,
  "doctype": "Role",
  "form_sidebar": 0,
  "home_page": null,
  "is_custom": 0,
  "list_sidebar": 0,
  "modified": "2022-05-27 11:02:18.513931",
  "name": "Fleet Manager",
  "notifications": 0,
  "restrict_to_domain": null,
  "role_name": "Fleet Manager",
  "search_bar": 0,
  "timeline": 0,
  "two_factor_auth": 0,
  "view_switcher": 0
 },
 {
  "bulk_actions": 0,
  "dashboard": 0,
  "desk_access": 1,
  "disabled": 0,
  "docstatus": 0,
  "doctype": "Role",
  "form_sidebar": 0,
  "home_page": null,
  "is_custom": 0,
  "list_sidebar": 0,
  "modified": "2022-05-27 11:02:23.916805",
  "name": "Expense Approver",
  "notifications": 0,
  "restrict_to_domain": null,
  "role_name": "Expense Approver",
  "search_bar": 0,
  "timeline": 0,
  "two_factor_auth": 0,
  "view_switcher": 0
 },
 {
  "bulk_actions": 0,
  "dashboard": 0,
  "desk_access": 1,
  "disabled": 0,
  "docstatus": 0,
  "doctype": "Role",
  "form_sidebar": 0,
  "home_page": null,
  "is_custom": 0,
  "list_sidebar": 0,
  "modified": "2022-05-27 11:02:25.428202",
  "name": "Interviewer",
  "notifications": 0,
  "restrict_to_domain": null,
  "role_name": "Interviewer",
  "search_bar": 0,
  "timeline": 0,
  "two_factor_auth": 0,
  "view_switcher": 0
 },
 {
  "bulk_actions": 0,
  "dashboard": 0,
  "desk_access": 1,
  "disabled": 0,
  "docstatus": 0,
  "doctype": "Role",
  "form_sidebar": 0,
  "home_page": null,
  "is_custom": 0,
  "list_sidebar": 0,
  "modified": "2022-05-27 11:02:27.861820",
  "name": "Leave Approver",
  "notifications": 0,
  "restrict_to_domain": null,
  "role_name": "Leave Approver",
  "search_bar": 0,
  "timeline": 0,
  "two_factor_auth": 0,
  "view_switcher": 0
 },
 {
  "bulk_actions": 0,
  "dashboard": 0,
  "desk_access": 1,
  "disabled": 0,
  "docstatus": 0,
  "doctype": "Role",
  "form_sidebar": 0,
  "home_page": null,
  "is_custom": 0,
  "list_sidebar": 0,
  "modified": "2022-05-27 11:02:36.051581",
  "name": "Quality Manager",
  "notifications": 0,
  "restrict_to_domain": null,
  "role_name": "Quality Manager",
  "search_bar": 0,
  "timeline": 0,
  "two_factor_auth": 0,
  "view_switcher": 0
 },
 {
  "bulk_actions": 0,
  "dashboard": 0,
  "desk_access": 1,
  "disabled": 0,
  "docstatus": 0,
  "doctype": "Role",
  "form_sidebar": 0,
  "home_page": null,
  "is_custom": 0,
  "list_sidebar": 0,
  "modified": "2022-05-27 11:02:40.772439",
  "name": "Fulfillment User",
  "notifications": 0,
  "restrict_to_domain": null,
  "role_name": "Fulfillment User",
  "search_bar": 0,
  "timeline": 0,
  "two_factor_auth": 0,
  "view_switcher": 0
 },
 {
  "bulk_actions": 0,
  "dashboard": 0,
  "desk_access": 1,
  "disabled": 0,
  "docstatus": 0,
  "doctype": "Role",
  "form_sidebar": 0,
  "home_page": null,
  "is_custom": 0,
  "list_sidebar": 0,
  "modified": "2022-05-27 11:02:46.575908",
  "name": "Support Team",
  "notifications": 0,
  "restrict_to_domain": null,
  "role_name": "Support Team",
  "search_bar": 0,
  "timeline": 0,
  "two_factor_auth": 0,
  "view_switcher": 0
 },
 {
  "bulk_actions": 0,
  "dashboard": 0,
  "desk_access": 1,
  "disabled": 0,
  "docstatus": 0,
  "doctype": "Role",
  "form_sidebar": 0,
  "home_page": null,
  "is_custom": 0,
  "list_sidebar": 0,
  "modified": "2022-05-27 11:02:47.506023",
  "name": "Agriculture User",
  "notifications": 0,
  "restrict_to_domain": null,
  "role_name": "Agriculture User",
  "search_bar": 0,
  "timeline": 0,
  "two_factor_auth": 0,
  "view_switcher": 0
 },
 {
  "bulk_actions": 0,
  "dashboard": 0,
  "desk_access": 1,
  "disabled": 0,
  "docstatus": 0,
  "doctype": "Role",
  "form_sidebar": 0,
  "home_page": null,
  "is_custom": 0,
  "list_sidebar": 0,
  "modified": "2022-05-27 11:02:47.565646",
  "name": "Agriculture Manager",
  "notifications": 0,
  "restrict_to_domain": null,
  "role_name": "Agriculture Manager",
  "search_bar": 0,
  "timeline": 0,
  "two_factor_auth": 0,
  "view_switcher": 0
 },
 {
  "bulk_actions": 0,
  "dashboard": 0,
  "desk_access": 1,
  "disabled": 0,
  "docstatus": 0,
  "doctype": "Role",
  "form_sidebar": 0,
  "home_page": null,
  "is_custom": 0,
  "list_sidebar": 0,
  "modified": "2022-05-27 11:02:56.719749",
  "name": "Loan Manager",
  "notifications": 0,
  "restrict_to_domain": null,
  "role_name": "Loan Manager",
  "search_bar": 0,
  "timeline": 0,
  "two_factor_auth": 0,
  "view_switcher": 0
 },
 {
  "bulk_actions": 0,
  "dashboard": 0,
  "desk_access": 0,
  "disabled": 0,
  "docstatus": 0,
  "doctype": "Role",
  "form_sidebar": 0,
  "home_page": null,
  "is_custom": 0,
  "list_sidebar": 0,
  "modified": "2022-07-28 21:11:42.753318",
  "name": "Supplier",
  "notifications": 0,
  "restrict_to_domain": null,
  "role_name": "Supplier",
  "search_bar": 0,
  "timeline": 0,
  "two_factor_auth": 0,
  "view_switcher": 0
 },
 {
  "bulk_actions": 1,
  "dashboard": 1,
  "desk_access": 1,
  "disabled": 0,
  "docstatus": 0,
  "doctype": "Role",
  "form_sidebar": 1,
  "home_page": null,
  "is_custom": 0,
  "list_sidebar": 1,
  "modified": "2022-05-27 11:03:12.684877",
  "name": "Analytics",
  "notifications": 1,
  "restrict_to_domain": null,
  "role_name": "Analytics",
  "search_bar": 1,
  "timeline": 1,
  "two_factor_auth": 0,
  "view_switcher": 1
 },
 {
  "bulk_actions": 1,
  "dashboard": 1,
  "desk_access": 1,
  "disabled": 0,
  "docstatus": 0,
  "doctype": "Role",
  "form_sidebar": 1,
  "home_page": null,
  "is_custom": 1,
  "list_sidebar": 1,
  "modified": "2022-05-27 11:03:15.898864",
  "name": "Employee Self Service",
  "notifications": 1,
  "restrict_to_domain": null,
  "role_name": "Employee Self Service",
  "search_bar": 1,
  "timeline": 1,
  "two_factor_auth": 0,
  "view_switcher": 1
 },
 {
  "bulk_actions": 0,
  "dashboard": 0,
  "desk_access": 0,
  "disabled": 0,
  "docstatus": 0,
  "doctype": "Role",
  "form_sidebar": 0,
  "home_page": null,
  "is_custom": 0,
  "list_sidebar": 0,
  "modified": "2022-07-28 20:24:35.883410",
  "name": "Ext Customer",
  "notifications": 0,
  "restrict_to_domain": null,
  "role_name": "Ext Customer",
  "search_bar": 0,
  "timeline": 0,
  "two_factor_auth": 0,
  "view_switcher": 0
 },
 {
  "bulk_actions": 1,
  "dashboard": 1,
  "desk_access": 1,
  "disabled": 0,
  "docstatus": 0,
  "doctype": "Role",
  "form_sidebar": 1,
  "home_page": null,
  "is_custom": 0,
  "list_sidebar": 1,
  "modified": "2022-08-31 19:03:04.969267",
  "name": "Read All",
  "notifications": 1,
  "restrict_to_domain": null,
  "role_name": "Read All",
  "search_bar": 1,
  "timeline": 1,
  "two_factor_auth": 0,
  "view_switcher": 1
 },
 {
  "bulk_actions": 1,
  "dashboard": 1,
  "desk_access": 1,
  "disabled": 0,
  "docstatus": 0,
  "doctype": "Role",
  "form_sidebar": 1,
  "home_page": null,
  "is_custom": 0,
  "list_sidebar": 1,
  "modified": "2022-09-08 22:33:09.512514",
  "name": "ERP Consultant",
  "notifications": 1,
  "restrict_to_domain": null,
  "role_name": "ERP Consultant",
  "search_bar": 1,
  "timeline": 1,
  "two_factor_auth": 0,
  "view_switcher": 1
 },
 {
  "bulk_actions": 1,
  "dashboard": 1,
  "desk_access": 1,
  "disabled": 0,
  "docstatus": 0,
  "doctype": "Role",
  "form_sidebar": 1,
  "home_page": null,
  "is_custom": 0,
  "list_sidebar": 1,
  "modified": "2022-09-22 11:13:15.066907",
  "name": "Z_Basis Support Consultant",
  "notifications": 1,
  "restrict_to_domain": null,
  "role_name": "Z_Basis Support Consultant",
  "search_bar": 1,
  "timeline": 1,
  "two_factor_auth": 0,
  "view_switcher": 1
 },
 {
  "bulk_actions": 1,
  "dashboard": 1,
  "desk_access": 1,
  "disabled": 0,
  "docstatus": 0,
  "doctype": "Role",
  "form_sidebar": 1,
  "home_page": null,
  "is_custom": 0,
  "list_sidebar": 1,
  "modified": "2022-09-30 11:28:15.683069",
  "name": "Issue_All",
  "notifications": 1,
  "restrict_to_domain": null,
  "role_name": "Issue_All",
  "search_bar": 1,
  "timeline": 1,
  "two_factor_auth": 0,
  "view_switcher": 1
 },
 {
  "bulk_actions": 1,
  "dashboard": 1,
  "desk_access": 1,
  "disabled": 0,
  "docstatus": 0,
  "doctype": "Role",
  "form_sidebar": 1,
  "home_page": null,
  "is_custom": 0,
  "list_sidebar": 1,
  "modified": "2022-09-30 13:14:06.508189",
  "name": "Basis Support Lead",
  "notifications": 1,
  "restrict_to_domain": null,
  "role_name": "Basis Support Lead",
  "search_bar": 1,
  "timeline": 1,
  "two_factor_auth": 0,
  "view_switcher": 1
 },
 {
  "bulk_actions": 1,
  "dashboard": 1,
  "desk_access": 1,
  "disabled": 0,
  "docstatus": 0,
  "doctype": "Role",
  "form_sidebar": 1,
  "home_page": null,
  "is_custom": 0,
  "list_sidebar": 1,
  "modified": "2022-11-02 13:38:11.076064",
  "name": "Z_Dinord_SAP_Support_Consultant",
  "notifications": 1,
  "restrict_to_domain": null,
  "role_name": "Z_Dinord_SAP_Support_Consultant",
  "search_bar": 1,
  "timeline": 1,
  "two_factor_auth": 0,
  "view_switcher": 1
 },
 {
  "bulk_actions": 1,
  "dashboard": 1,
  "desk_access": 1,
  "disabled": 0,
  "docstatus": 0,
  "doctype": "Role",
  "form_sidebar": 1,
  "home_page": null,
  "is_custom": 0,
  "list_sidebar": 1,
  "modified": "2022-11-02 15:56:03.923112",
  "name": "Z_Dinord_SAP_Team_Lead",
  "notifications": 1,
  "restrict_to_domain": null,
  "role_name": "Z_Dinord_SAP_Team_Lead",
  "search_bar": 1,
  "timeline": 1,
  "two_factor_auth": 0,
  "view_switcher": 1
 },
 {
  "bulk_actions": 1,
  "dashboard": 1,
  "desk_access": 1,
  "disabled": 0,
  "docstatus": 0,
  "doctype": "Role",
  "form_sidebar": 1,
  "home_page": null,
  "is_custom": 0,
  "list_sidebar": 1,
  "modified": "2022-11-02 16:09:07.135198",
  "name": "Z_Dinord_SAP_Project_Manager",
  "notifications": 1,
  "restrict_to_domain": null,
  "role_name": "Z_Dinord_SAP_Project_Manager",
  "search_bar": 1,
  "timeline": 1,
  "two_factor_auth": 0,
  "view_switcher": 1
 },
 {
  "bulk_actions": 1,
  "dashboard": 1,
  "desk_access": 1,
  "disabled": 0,
  "docstatus": 0,
  "doctype": "Role",
  "form_sidebar": 1,
  "home_page": null,
  "is_custom": 0,
  "list_sidebar": 1,
  "modified": "2022-11-02 16:12:45.946508",
  "name": "Z_Dinord_SAP_Dispatcher",
  "notifications": 1,
  "restrict_to_domain": null,
  "role_name": "Z_Dinord_SAP_Dispatcher",
  "search_bar": 1,
  "timeline": 1,
  "two_factor_auth": 0,
  "view_switcher": 1
 },
 {
  "bulk_actions": 1,
  "dashboard": 1,
  "desk_access": 1,
  "disabled": 0,
  "docstatus": 0,
  "doctype": "Role",
  "form_sidebar": 0,
  "home_page": null,
  "is_custom": 0,
  "list_sidebar": 0,
  "modified": "2022-11-03 13:29:40.896044",
  "name": "Z_Dinord_SAP_Issue_Creator",
  "notifications": 1,
  "restrict_to_domain": null,
  "role_name": "Z_Dinord_SAP_Issue_Creator",
  "search_bar": 1,
  "timeline": 1,
  "two_factor_auth": 0,
  "view_switcher": 1
 },
 {
  "bulk_actions": 1,
  "dashboard": 1,
  "desk_access": 1,
  "disabled": 0,
  "docstatus": 0,
  "doctype": "Role",
  "form_sidebar": 1,
  "home_page": null,
  "is_custom": 0,
  "list_sidebar": 1,
  "modified": "2022-11-23 18:25:06.761094",
  "name": "Z_Dinord_Notifications",
  "notifications": 1,
  "restrict_to_domain": null,
  "role_name": "Z_Dinord_Notifications",
  "search_bar": 1,
  "timeline": 1,
  "two_factor_auth": 0,
  "view_switcher": 1
 },
 {
  "bulk_actions": 1,
  "dashboard": 1,
  "desk_access": 1,
  "disabled": 0,
  "docstatus": 0,
  "doctype": "Role",
  "form_sidebar": 1,
  "home_page": null,
  "is_custom": 0,
  "list_sidebar": 1,
  "modified": "2022-12-13 13:20:49.165039",
  "name": "Z_Dinord_Task_level_1_R",
  "notifications": 1,
  "restrict_to_domain": null,
  "role_name": "Z_Dinord_Task_level_1_R",
  "search_bar": 1,
  "timeline": 1,
  "two_factor_auth": 0,
  "view_switcher": 1
 },
 {
  "bulk_actions": 1,
  "dashboard": 1,
  "desk_access": 1,
  "disabled": 0,
  "docstatus": 0,
  "doctype": "Role",
  "form_sidebar": 1,
  "home_page": null,
  "is_custom": 0,
  "list_sidebar": 1,
  "modified": "2022-12-13 13:38:28.113357",
  "name": "Z_Dinord_Task_Level_1_W",
  "notifications": 1,
  "restrict_to_domain": null,
  "role_name": "Z_Dinord_Task_Level_1_W",
  "search_bar": 1,
  "timeline": 1,
  "two_factor_auth": 0,
  "view_switcher": 1
 },
 {
  "bulk_actions": 1,
  "dashboard": 1,
  "desk_access": 1,
  "disabled": 1,
  "docstatus": 0,
  "doctype": "Role",
  "form_sidebar": 1,
  "home_page": null,
  "is_custom": 0,
  "list_sidebar": 1,
  "modified": "2023-03-16 21:45:19.094964",
  "name": "Z_Dinord_Assigned_Issue_Only",
  "notifications": 1,
  "restrict_to_domain": null,
  "role_name": "Z_Dinord_Assigned_Issue_Only",
  "search_bar": 1,
  "timeline": 1,
  "two_factor_auth": 0,
  "view_switcher": 1
 },
 {
  "bulk_actions": 1,
  "dashboard": 1,
  "desk_access": 1,
  "disabled": 1,
  "docstatus": 0,
  "doctype": "Role",
  "form_sidebar": 1,
  "home_page": null,
  "is_custom": 0,
  "list_sidebar": 1,
  "modified": "2023-03-16 21:45:24.554428",
  "name": "Z_Dinord_Assigned_Item_Only",
  "notifications": 1,
  "restrict_to_domain": null,
  "role_name": "Z_Dinord_Assigned_Item_Only",
  "search_bar": 1,
  "timeline": 1,
  "two_factor_auth": 0,
  "view_switcher": 1
 },
 {
  "bulk_actions": 1,
  "dashboard": 1,
  "desk_access": 1,
  "disabled": 1,
  "docstatus": 0,
  "doctype": "Role",
  "form_sidebar": 1,
  "home_page": null,
  "is_custom": 0,
  "list_sidebar": 1,
  "modified": "2023-03-16 21:45:29.599182",
  "name": "Z_Dinord_Assigned_Lead_Only",
  "notifications": 1,
  "restrict_to_domain": null,
  "role_name": "Z_Dinord_Assigned_Lead_Only",
  "search_bar": 1,
  "timeline": 1,
  "two_factor_auth": 0,
  "view_switcher": 1
 },
 {
  "bulk_actions": 1,
  "dashboard": 1,
  "desk_access": 1,
  "disabled": 1,
  "docstatus": 0,
  "doctype": "Role",
  "form_sidebar": 1,
  "home_page": null,
  "is_custom": 0,
  "list_sidebar": 1,
  "modified": "2023-03-16 21:45:37.425063",
  "name": "Z_Dinord_Assigned_Opportunity_Only",
  "notifications": 1,
  "restrict_to_domain": null,
  "role_name": "Z_Dinord_Assigned_Opportunity_Only",
  "search_bar": 1,
  "timeline": 1,
  "two_factor_auth": 0,
  "view_switcher": 1
 },
 {
  "bulk_actions": 1,
  "dashboard": 1,
  "desk_access": 1,
  "disabled": 1,
  "docstatus": 0,
  "doctype": "Role",
  "form_sidebar": 1,
  "home_page": null,
  "is_custom": 0,
  "list_sidebar": 1,
  "modified": "2023-03-16 21:45:41.782961",
  "name": "Z_Dinord_Assigned_Project_Only",
  "notifications": 1,
  "restrict_to_domain": null,
  "role_name": "Z_Dinord_Assigned_Project_Only",
  "search_bar": 1,
  "timeline": 1,
  "two_factor_auth": 0,
  "view_switcher": 1
 },
 {
  "bulk_actions": 1,
  "dashboard": 1,
  "desk_access": 1,
  "disabled": 1,
  "docstatus": 0,
  "doctype": "Role",
  "form_sidebar": 1,
  "home_page": null,
  "is_custom": 0,
  "list_sidebar": 1,
  "modified": "2023-03-16 21:45:48.135322",
  "name": "Z_Dinord_Assigned_Prospect_Only",
  "notifications": 1,
  "restrict_to_domain": null,
  "role_name": "Z_Dinord_Assigned_Prospect_Only",
  "search_bar": 1,
  "timeline": 1,
  "two_factor_auth": 0,
  "view_switcher": 1
 },
 {
  "bulk_actions": 1,
  "dashboard": 1,
  "desk_access": 1,
  "disabled": 1,
  "docstatus": 0,
  "doctype": "Role",
  "form_sidebar": 1,
  "home_page": null,
  "is_custom": 0,
  "list_sidebar": 1,
  "modified": "2023-03-16 21:45:53.333803",
  "name": "Z_Dinord_Assigned_Task_Only",
  "notifications": 1,
  "restrict_to_domain": null,
  "role_name": "Z_Dinord_Assigned_Task_Only",
  "search_bar": 1,
  "timeline": 1,
  "two_factor_auth": 0,
  "view_switcher": 1
 },
 {
  "bulk_actions": 1,
  "dashboard": 1,
  "desk_access": 1,
  "disabled": 0,
  "docstatus": 0,
  "doctype": "Role",
  "form_sidebar": 1,
  "home_page": null,
  "is_custom": 0,
  "list_sidebar": 1,
  "modified": "2023-02-03 17:09:43.732965",
  "name": "Z_Dinord_Sales_Manager",
  "notifications": 1,
  "restrict_to_domain": null,
  "role_name": "Z_Dinord_Sales_Manager",
  "search_bar": 1,
  "timeline": 1,
  "two_factor_auth": 0,
  "view_switcher": 1
 },
 {
  "bulk_actions": 1,
  "dashboard": 1,
  "desk_access": 1,
  "disabled": 0,
  "docstatus": 0,
  "doctype": "Role",
  "form_sidebar": 1,
  "home_page": null,
  "is_custom": 0,
  "list_sidebar": 1,
  "modified": "2023-02-10 17:54:58.065127",
  "name": "Z_Dinord_Sales_Lead",
  "notifications": 1,
  "restrict_to_domain": null,
  "role_name": "Z_Dinord_Sales_Lead",
  "search_bar": 1,
  "timeline": 1,
  "two_factor_auth": 0,
  "view_switcher": 1
 },
 {
  "bulk_actions": 1,
  "dashboard": 1,
  "desk_access": 1,
  "disabled": 0,
  "docstatus": 0,
  "doctype": "Role",
  "form_sidebar": 1,
  "home_page": null,
  "is_custom": 0,
  "list_sidebar": 1,
  "modified": "2023-02-17 16:27:54.859848",
  "name": "Z_Dinord_SAP_Customer_manager",
  "notifications": 1,
  "restrict_to_domain": null,
  "role_name": "Z_Dinord_SAP_Customer_manager",
  "search_bar": 1,
  "timeline": 1,
  "two_factor_auth": 0,
  "view_switcher": 1
 },
 {
  "bulk_actions": 1,
  "dashboard": 1,
  "desk_access": 1,
  "disabled": 0,
  "docstatus": 0,
  "doctype": "Role",
  "form_sidebar": 1,
  "home_page": null,
  "is_custom": 0,
  "list_sidebar": 1,
  "modified": "2023-02-27 01:42:55.544540",
  "name": "Z_Dinord_Test",
  "notifications": 1,
  "restrict_to_domain": null,
  "role_name": "Z_Dinord_Test",
  "search_bar": 1,
  "timeline": 1,
  "two_factor_auth": 0,
  "view_switcher": 1
 },
 {
  "bulk_actions": 1,
  "dashboard": 1,
  "desk_access": 1,
  "disabled": 0,
  "docstatus": 0,
  "doctype": "Role",
  "form_sidebar": 1,
  "home_page": null,
  "is_custom": 0,
  "list_sidebar": 1,
  "modified": "2023-03-14 19:53:56.019468",
  "name": "Z_Dinord_Sales_Select_DocTypes",
  "notifications": 1,
  "restrict_to_domain": null,
  "role_name": "Z_Dinord_Sales_Select_DocTypes",
  "search_bar": 1,
  "timeline": 1,
  "two_factor_auth": 0,
  "view_switcher": 1
 },
 {
  "bulk_actions": 1,
  "dashboard": 1,
  "desk_access": 1,
  "disabled": 0,
  "docstatus": 0,
  "doctype": "Role",
  "form_sidebar": 1,
  "home_page": null,
  "is_custom": 0,
  "list_sidebar": 1,
  "modified": "2023-04-03 18:21:52.279498",
  "name": "Z_Dinord_Demand_Manager",
  "notifications": 1,
  "restrict_to_domain": null,
  "role_name": "Z_Dinord_Demand_Manager",
  "search_bar": 1,
  "timeline": 1,
  "two_factor_auth": 0,
  "view_switcher": 1
 },
 {
  "bulk_actions": 1,
  "dashboard": 1,
  "desk_access": 1,
  "disabled": 0,
  "docstatus": 0,
  "doctype": "Role",
  "form_sidebar": 1,
  "home_page": null,
  "is_custom": 0,
  "list_sidebar": 1,
  "modified": "2023-04-03 18:23:40.869463",
  "name": "Z_Dinord_Marketing_Manager",
  "notifications": 1,
  "restrict_to_domain": null,
  "role_name": "Z_Dinord_Marketing_Manager",
  "search_bar": 1,
  "timeline": 1,
  "two_factor_auth": 0,
  "view_switcher": 1
 },
 {
  "bulk_actions": 1,
  "dashboard": 1,
  "desk_access": 1,
  "disabled": 0,
  "docstatus": 0,
  "doctype": "Role",
  "form_sidebar": 1,
  "home_page": null,
  "is_custom": 0,
  "list_sidebar": 1,
  "modified": "2023-04-13 18:02:02.705528",
  "name": "Z_Dinord_Management",
  "notifications": 1,
  "restrict_to_domain": null,
  "role_name": "Z_Dinord_Management",
  "search_bar": 1,
  "timeline": 1,
  "two_factor_auth": 0,
  "view_switcher": 1
 },
 {
  "bulk_actions": 1,
  "dashboard": 1,
  "desk_access": 1,
  "disabled": 0,
  "docstatus": 0,
  "doctype": "Role",
  "form_sidebar": 1,
  "home_page": null,
  "is_custom": 0,
  "list_sidebar": 1,
  "modified": "2023-04-24 17:53:45.165546",
  "name": "Z_Dinord_Data_Import",
  "notifications": 1,
  "restrict_to_domain": null,
  "role_name": "Z_Dinord_Data_Import",
  "search_bar": 1,
  "timeline": 1,
  "two_factor_auth": 0,
  "view_switcher": 1
 },
 {
  "bulk_actions": 1,
  "dashboard": 1,
  "desk_access": 1,
  "disabled": 0,
  "docstatus": 0,
  "doctype": "Role",
  "form_sidebar": 1,
  "home_page": null,
  "is_custom": 0,
  "list_sidebar": 1,
  "modified": "2023-04-27 11:49:22.352009",
  "name": "Z_Milestone",
  "notifications": 1,
  "restrict_to_domain": null,
  "role_name": "Z_Milestone",
  "search_bar": 1,
  "timeline": 1,
  "two_factor_auth": 0,
  "view_switcher": 1
 },
 {
  "bulk_actions": 1,
  "dashboard": 1,
  "desk_access": 1,
  "disabled": 0,
  "docstatus": 0,
  "doctype": "Role",
  "form_sidebar": 1,
  "home_page": null,
  "is_custom": 0,
  "list_sidebar": 1,
  "modified": "2023-05-12 16:21:06.093561",
  "name": "Z_Dinord_User",
  "notifications": 1,
  "restrict_to_domain": null,
  "role_name": "Z_Dinord_User",
  "search_bar": 1,
  "timeline": 1,
  "two_factor_auth": 0,
  "view_switcher": 1
 },
 {
  "bulk_actions": 1,
  "dashboard": 1,
  "desk_access": 1,
  "disabled": 0,
  "docstatus": 0,
  "doctype": "Role",
  "form_sidebar": 1,
  "home_page": null,
  "is_custom": 0,
  "list_sidebar": 1,
  "modified": "2023-07-14 16:39:46.309838",
  "name": "Consultant",
  "notifications": 1,
  "restrict_to_domain": null,
  "role_name": "Consultant",
  "search_bar": 1,
  "timeline": 1,
  "two_factor_auth": 0,
  "view_switcher": 1
 },
 {
  "bulk_actions": 1,
  "dashboard": 1,
  "desk_access": 1,
  "disabled": 0,
  "docstatus": 0,
  "doctype": "Role",
  "form_sidebar": 1,
  "home_page": null,
  "is_custom": 0,
  "list_sidebar": 1,
  "modified": "2023-07-14 16:40:20.188481",
  "name": "Z_Dinord_ABAP_Manager",
  "notifications": 1,
  "restrict_to_domain": null,
  "role_name": "Z_Dinord_ABAP_Manager",
  "search_bar": 1,
  "timeline": 1,
  "two_factor_auth": 0,
  "view_switcher": 1
 },
 {
  "bulk_actions": 1,
  "dashboard": 1,
  "desk_access": 1,
  "disabled": 0,
  "docstatus": 0,
  "doctype": "Role",
  "form_sidebar": 1,
  "home_page": null,
  "is_custom": 0,
  "list_sidebar": 1,
  "modified": "2023-07-14 16:40:29.832987",
  "name": "Z_Dinord_ABAP _Developer",
  "notifications": 1,
  "restrict_to_domain": null,
  "role_name": "Z_Dinord_ABAP _Developer",
  "search_bar": 1,
  "timeline": 1,
  "two_factor_auth": 0,
  "view_switcher": 1
 },
 {
  "bulk_actions": 1,
  "dashboard": 1,
  "desk_access": 1,
  "disabled": 0,
  "docstatus": 0,
  "doctype": "Role",
  "form_sidebar": 1,
  "home_page": null,
  "is_custom": 0,
  "list_sidebar": 1,
  "modified": "2023-08-22 05:07:41.734637",
  "name": "Moderator",
  "notifications": 1,
  "restrict_to_domain": null,
  "role_name": "Moderator",
  "search_bar": 1,
  "timeline": 1,
  "two_factor_auth": 0,
  "view_switcher": 1
 },
 {
  "bulk_actions": 1,
  "dashboard": 1,
  "desk_access": 1,
  "disabled": 0,
  "docstatus": 0,
  "doctype": "Role",
  "form_sidebar": 1,
  "home_page": null,
  "is_custom": 0,
  "list_sidebar": 1,
  "modified": "2023-08-22 05:07:41.774692",
  "name": "Class Evaluator",
  "notifications": 1,
  "restrict_to_domain": null,
  "role_name": "Class Evaluator",
  "search_bar": 1,
  "timeline": 1,
  "two_factor_auth": 0,
  "view_switcher": 1
 },
 {
  "bulk_actions": 0,
  "dashboard": 0,
  "desk_access": 0,
  "disabled": 0,
  "docstatus": 0,
  "doctype": "Role",
  "form_sidebar": 0,
  "home_page": "",
  "is_custom": 0,
  "list_sidebar": 0,
  "modified": "2023-08-22 05:07:58.338288",
  "name": "Course Creator",
  "notifications": 0,
  "restrict_to_domain": null,
  "role_name": "Course Creator",
  "search_bar": 0,
  "timeline": 0,
  "two_factor_auth": 0,
  "view_switcher": 0
 },
 {
  "bulk_actions": 0,
  "dashboard": 0,
  "desk_access": 1,
  "disabled": 0,
  "docstatus": 0,
  "doctype": "Role",
  "form_sidebar": 0,
  "home_page": null,
  "is_custom": 0,
  "list_sidebar": 0,
  "modified": "2022-12-07 21:36:44.284615",
  "name": "Insights Admin",
  "notifications": 0,
  "restrict_to_domain": null,
  "role_name": "Insights Admin",
  "search_bar": 0,
  "timeline": 0,
  "two_factor_auth": 0,
  "view_switcher": 0
 },
 {
  "bulk_actions": 0,
  "dashboard": 0,
  "desk_access": 0,
  "disabled": 0,
  "docstatus": 0,
  "doctype": "Role",
  "form_sidebar": 0,
  "home_page": null,
  "is_custom": 0,
  "list_sidebar": 0,
  "modified": "2022-12-07 21:36:44.121244",
  "name": "Insights User",
  "notifications": 0,
  "restrict_to_domain": null,
  "role_name": "Insights User",
  "search_bar": 0,
  "timeline": 0,
  "two_factor_auth": 0,
  "view_switcher": 0
 }
]